pypelined/__about__.py
pypelined/__init__.py
pypelined/__main__.py
pypelined/driver.py
pypelined/conf/__init__.py
pypelined/conf/loader.py
pypelined/conf/logger.py
pypelined/consumer/__init__.py
pypelined/consumer/alice_apmon.py
pypelined/consumer/socket.py
pypelined/consumer/telegraf.py
pypelined/modifier/__init__.py
pypelined/modifier/dictlets.py
pypelined/provider/__init__.py
pypelined/provider/stream.py
pypelined/provider/xrootd.py
pypelined/utilities/__init__.py
pypelined/utilities/dfs_counter.py
pypelined/utilities/proctools.py
pypelined/utilities/singleton.py
pypelined-0.1.5.dist-info/LICENSE.txt
pypelined-0.1.5.dist-info/METADATA
pypelined-0.1.5.dist-info/WHEEL
pypelined-0.1.5.dist-info/top_level.txt
pypelined-0.1.5.dist-info/RECORD
