Metadata-Version: 2.1
Name: pypelined
Version: 0.1.5
Summary: stream and pipeline processing service
Home-page: https://github.com/maxfischer2781/pypelined
Author: Max Fischer
Author-email: maxfischer2781@gmail.com
License: MIT
Keywords: pipeline service stream pypeline
Classifier: Development Status :: 4 - Beta
Classifier: Intended Audience :: Developers
Classifier: Intended Audience :: System Administrators
Classifier: Topic :: System :: Monitoring
Classifier: Programming Language :: Python :: 2
Classifier: Programming Language :: Python :: 2.6
Classifier: Programming Language :: Python :: 2.7
Classifier: Programming Language :: Python :: 3
Classifier: Programming Language :: Python :: 3.3
Classifier: Programming Language :: Python :: 3.4
Classifier: Programming Language :: Python :: 3.5
Classifier: Programming Language :: Python :: 3.6
License-File: LICENSE.txt
Requires-Dist: apmon
Requires-Dist: filelock
Requires-Dist: chainlet >=1.2.0
Requires-Dist: include
